jupyter_kernel_mcp/__init__.py
jupyter_kernel_mcp/server.py
jupyter_kernel_mcp-0.2.0.dist-info/METADATA
jupyter_kernel_mcp-0.2.0.dist-info/WHEEL
jupyter_kernel_mcp-0.2.0.dist-info/entry_points.txt
jupyter_kernel_mcp-0.2.0.dist-info/RECORD
