Metadata-Version: 2.4
Name: jupyter-kernel-mcp
Version: 0.2.0
Summary: MCP server for stateful Jupyter kernel development with multi-language support (Python, TypeScript, JavaScript)
Project-URL: Homepage, https://github.com/codewithcheese/jupyter-kernel-mcp
Project-URL: Repository, https://github.com/codewithcheese/jupyter-kernel-mcp.git
Project-URL: Issues, https://github.com/codewithcheese/jupyter-kernel-mcp/issues
Author-email: Tom M <tom@codewithcheese.com>
License: MIT
Keywords: ai,assistant,jupyter,kernel,mcp
Classifier: Development Status :: 3 - Alpha
Classifier: Intended Audience :: Developers
Classifier: License :: OSI Approved :: MIT License
Classifier: Programming Language :: Python :: 3
Classifier: Programming Language :: Python :: 3.10
Classifier: Programming Language :: Python :: 3.11
Classifier: Programming Language :: Python :: 3.12
Classifier: Programming Language :: Python :: 3.13
Classifier: Topic :: Scientific/Engineering
Classifier: Topic :: Software Development :: Libraries :: Python Modules
Requires-Python: >=3.10
Requires-Dist: ipykernel>=6.0.0
Requires-Dist: jupyter-client>=7.0.0
Requires-Dist: mcp>=1.0.0
